wizardsdata/__init__.py
wizardsdata/cli.py
wizardsdata/config.py
wizardsdata/generator.py
wizardsdata/templates.py
wizardsdata/utils.py
wizardsdata-0.1.0.dist-info/LICENSE
wizardsdata-0.1.0.dist-info/METADATA
wizardsdata-0.1.0.dist-info/WHEEL
wizardsdata-0.1.0.dist-info/entry_points.txt
wizardsdata-0.1.0.dist-info/top_level.txt
wizardsdata-0.1.0.dist-info/RECORD
