Metadata-Version: 2.2
Name: wizardsdata
Version: 0.1.0
Summary: library for generating conversation datasets using language models
Home-page: https://github.com/peremartra/WizardSData
Author: Pere Martra
Author-email: peremartra@uadla.com
Project-URL: Documentation, https://peremartra.github.io/WizardSData/
Project-URL: Bug Tracker, https://github.com/peremartra/WizardSData/issues
Classifier: Programming Language :: Python :: 3
Classifier: License :: OSI Approved :: Apache Software License
Classifier: Operating System :: OS Independent
Classifier: Topic :: Scientific/Engineering :: Artificial Intelligence
Classifier: Topic :: Software Development :: Libraries :: Python Modules
Classifier: Intended Audience :: Developers
Classifier: Intended Audience :: Science/Research
Requires-Python: >=3.7
License-File: LICENSE
Requires-Dist: openai>=1.0.0
Requires-Dist: jinja2>=3.0.0
Dynamic: author
Dynamic: author-email
Dynamic: classifier
Dynamic: description
Dynamic: description-content-type
Dynamic: home-page
Dynamic: project-url
Dynamic: requires-dist
Dynamic: requires-python
Dynamic: summary
